AUTHORS
CHANGELOG
INSTALL
LICENSE
MANIFEST.in
README
setup.py
django_reg.egg-info/PKG-INFO
django_reg.egg-info/SOURCES.txt
django_reg.egg-info/dependency_links.txt
django_reg.egg-info/top_level.txt
docs/Makefile
docs/conf.py
docs/default-backend.rst
docs/faq.rst
docs/forms.rst
docs/index.rst
docs/make.bat
docs/quickstart.rst
docs/release-notes.rst
docs/signals.rst
docs/simple-backend.rst
docs/upgrade.rst
docs/views.rst
registration/__init__.py
registration/admin.py
registration/auth_urls.py
registration/forms.py
registration/models.py
registration/signals.py
registration/urls.py
registration/views.py
registration/backends/__init__.py
registration/backends/default/__init__.py
registration/backends/default/urls.py
registration/backends/default/views.py
registration/backends/simple/__init__.py
registration/backends/simple/urls.py
registration/backends/simple/views.py
registration/locale/ar/LC_MESSAGES/django.mo
registration/locale/ar/LC_MESSAGES/django.po
registration/locale/bg/LC_MESSAGES/django.mo
registration/locale/bg/LC_MESSAGES/django.po
registration/locale/ca/LC_MESSAGES/django.mo
registration/locale/ca/LC_MESSAGES/django.po
registration/locale/cs/LC_MESSAGES/django.mo
registration/locale/cs/LC_MESSAGES/django.po
registration/locale/da/LC_MESSAGES/django.mo
registration/locale/da/LC_MESSAGES/django.po
registration/locale/de/LC_MESSAGES/django.mo
registration/locale/de/LC_MESSAGES/django.po
registration/locale/el/LC_MESSAGES/django.mo
registration/locale/el/LC_MESSAGES/django.po
registration/locale/en/LC_MESSAGES/django.mo
registration/locale/en/LC_MESSAGES/django.po
registration/locale/es/LC_MESSAGES/django.mo
registration/locale/es/LC_MESSAGES/django.po
registration/locale/es_AR/LC_MESSAGES/django.mo
registration/locale/es_AR/LC_MESSAGES/django.po
registration/locale/fa/LC_MESSAGES/django.mo
registration/locale/fa/LC_MESSAGES/django.po
registration/locale/fr/LC_MESSAGES/django.mo
registration/locale/fr/LC_MESSAGES/django.po
registration/locale/he/LC_MESSAGES/django.mo
registration/locale/he/LC_MESSAGES/django.po
registration/locale/hr/LC_MESSAGES/django.mo
