Metadata-Version: 1.0
Name: django-reg
Version: 1.0.1
Summary: An extensible user-registration application for Django
Home-page: http://www.bitbucket.org/pydanny/django-registration/
Author: Daniel Greenfeld (fork author)
Author-email: pydanny@gmail.com
License: UNKNOWN
Platform: UNKNOWN
Classifier: Development Status :: 5 - Production/Stable
Classifier: Environment :: Web Environment
Classifier: Framework :: Django
Classifier: Intended Audience :: Developers
Classifier: License :: OSI Approved :: BSD License
Classifier: Operating System :: OS Independent
Classifier: Programming Language :: Python :: 3.3
Classifier: Topic :: Software Development :: Libraries :: Python Modules
Classifier: Topic :: Utilities
